street_cred/__init__.py
street_cred/connection.py
street_cred/crypto.py
street_cred/models.py
street_cred/utils.py
street_cred-0.0.3.dist-info/LICENSE
street_cred-0.0.3.dist-info/METADATA
street_cred-0.0.3.dist-info/WHEEL
street_cred-0.0.3.dist-info/top_level.txt
street_cred-0.0.3.dist-info/RECORD
