Metadata-Version: 2.1
Name: street-cred
Version: 0.0.3
Summary: UNKNOWN
Home-page: UNKNOWN
Author: Aaron Mangum
Author-email: UNKNOWN
License: UNKNOWN
Platform: UNKNOWN
Requires-Dist: cryptography (~=2.9)
Requires-Dist: psycopg2-binary (~=2.8.5)
Requires-Dist: sqlalchemy (~=1.3.15)
